{
  "schema_version": 1,
  "records": [
    {
      "number": 1,
      "id": "poison",
      "name": "Poison",
      "source_version": "075",
      "attack_damage": 12,
      "damage_type": "wizardry",
      "behavior": {
        "kind": "direct_hit"
      },
      "target": "explicit",
      "target_restriction": "none",
      "range": 6,
      "implicit_target_range": 0,
      "hits_per_attack": 1,
      "moves_to_target": false,
      "moves_target": false,
      "element": "poison",
      "skip_elemental_modifier": false,
      "effect": "poisoned",
      "requirements": [
        {
          "stat": "total_energy",
          "value": 140
        }
      ],
      "consume": [
        {
          "stat": "current_mana",
          "value": 42
        }
      ],
      "classes": [
        "dark_wizard",
        "magic_gladiator"
      ]
    },
    {
      "number": 2,
      "id": "meteorite",
      "name": "Meteorite",
      "source_version": "075",
      "attack_damage": 21,
      "damage_type": "wizardry",
      "behavior": {
        "kind": "direct_hit"
      },
      "target": "explicit",
      "target_restriction": "none",
      "range": 6,
      "implicit_target_range": 0,
      "hits_per_attack": 1,
      "moves_to_target": false,
      "moves_target": false,
      "element": "earth",
      "skip_elemental_modifier": false,
      "effect": null,
      "requirements": [
        {
          "stat": "total_energy",
          "value": 104
        }
      ],
      "consume": [
        {
          "stat": "current_mana",
          "value": 12
        }
      ],
      "classes": [
        "dark_wizard",
        "magic_gladiator"
      ]
    },
    {
      "number": 3,
      "id": "lightning",
      "name": "Lightning",
      "source_version": "075",
      "attack_damage": 17,
      "damage_type": "wizardry",
      "behavior": {
        "kind": "direct_hit"
      },
      "target": "explicit",
      "target_restriction": "none",
      "range": 6,
      "implicit_target_range": 0,
      "hits_per_attack": 1,
      "moves_to_target": false,
      "moves_target": false,
      "element": "lightning",
      "skip_elemental_modifier": false,
      "effect": null,
      "requirements": [
        {
          "stat": "total_energy",
          "value": 72
        }
      ],
      "consume": [
        {
          "stat": "current_mana",
          "value": 15
        }
      ],
      "classes": [
        "dark_wizard",
        "magic_gladiator"
      ]
    },
    {
      "number": 4,
      "id": "fire_ball",
      "name": "Fire Ball",
      "source_version": "075",
      "attack_damage": 8,
      "damage_type": "wizardry",
      "behavior": {
        "kind": "direct_hit"
      },
      "target": "explicit",
      "target_restriction": "none",
      "range": 6,
      "implicit_target_range": 0,
      "hits_per_attack": 1,
      "moves_to_target": false,
      "moves_target": false,
      "element": "fire",
      "skip_elemental_modifier": false,
      "effect": null,
      "requirements": [
        {
          "stat": "total_energy",
          "value": 40
        }
      ],
      "consume": [
        {
          "stat": "current_mana",
          "value": 3
        }
      ],
      "classes": [
        "dark_wizard",
        "magic_gladiator"
      ]
    },
    {
      "number": 5,
      "id": "flame",
      "name": "Flame",
      "source_version": "075",
      "attack_damage": 25,
      "damage_type": "wizardry",
      "behavior": {
        "kind": "area_automatic",
        "area": {
          "geometry": {
            "kind": "circle",
            "diameter": 2.0
          },
          "deferred_hits": true,
          "delay_per_tile_ms": 0,
          "delay_between_hits_ms": 500,
          "hits_per_target": [
            0,
            2
          ],
          "hits_per_attack_range": [
            0,
            0
          ],
          "hit_chance_per_distance": 0.5,
          "projectile_count": 1,
          "effect_range": 0
        }
      },
      "target": "explicit",
      "target_restriction": "none",
      "range": 6,
      "implicit_target_range": 0,
      "hits_per_attack": 1,
      "moves_to_target": false,
      "moves_target": false,
      "element": "fire",
      "skip_elemental_modifier": false,
      "effect": null,
      "requirements": [
        {
          "stat": "total_energy",
          "value": 160
        }
      ],
      "consume": [
        {
          "stat": "current_mana",
          "value": 50
        }
      ],
      "classes": [
        "dark_wizard",
        "magic_gladiator"
      ]
    },
    {
      "number": 6,
      "id": "teleport",
      "name": "Teleport",
      "source_version": "075",
      "attack_damage": 0,
      "damage_type": "wizardry",
      "behavior": {
        "kind": "other"
      },
      "target": "explicit",
      "target_restriction": "none",
      "range": 6,
      "implicit_target_range": 0,
      "hits_per_attack": 1,
      "moves_to_target": false,
      "moves_target": false,
      "element": null,
      "skip_elemental_modifier": false,
      "effect": null,
      "requirements": [
        {
          "stat": "total_energy",
          "value": 88
        }
      ],
      "consume": [
        {
          "stat": "current_mana",
          "value": 30
        }
      ],
      "classes": [
        "dark_wizard"
      ]
    },
    {
      "number": 7,
      "id": "ice",
      "name": "Ice",
      "source_version": "075",
      "attack_damage": 10,
      "damage_type": "wizardry",
      "behavior": {
        "kind": "direct_hit"
      },
      "target": "explicit",
      "target_restriction": "none",
      "range": 6,
      "implicit_target_range": 0,
      "hits_per_attack": 1,
      "moves_to_target": false,
      "moves_target": false,
      "element": "ice",
      "skip_elemental_modifier": false,
      "effect": "iced",
      "requirements": [
        {
          "stat": "total_energy",
          "value": 120
        }
      ],
      "consume": [
        {
          "stat": "current_mana",
          "value": 38
        }
      ],
      "classes": [
        "dark_wizard",
        "magic_gladiator"
      ]
    },
    {
      "number": 8,
      "id": "twister",
      "name": "Twister",
      "source_version": "075",
      "attack_damage": 35,
      "damage_type": "wizardry",
      "behavior": {
        "kind": "area_automatic",
        "area": {
          "geometry": {
            "kind": "frustum",
            "start_width": 1.5,
            "end_width": 1.5,
            "distance": 4.0
          },
          "deferred_hits": true,
          "delay_per_tile_ms": 300,
          "delay_between_hits_ms": 1000,
          "hits_per_target": [
            0,
            2
          ],
          "hits_per_attack_range": [
            0,
            0
          ],
          "hit_chance_per_distance": 0.7,
          "projectile_count": 1,
          "effect_range": 0
        }
      },
      "target": "explicit",
      "target_restriction": "none",
      "range": 6,
      "implicit_target_range": 0,
      "hits_per_attack": 1,
      "moves_to_target": false,
      "moves_target": false,
      "element": "wind",
      "skip_elemental_modifier": false,
      "effect": null,
      "requirements": [
        {
          "stat": "total_energy",
          "value": 180
        }
      ],
      "consume": [
        {
          "stat": "current_mana",
          "value": 60
        }
      ],
      "classes": [
        "dark_wizard",
        "magic_gladiator"
      ]
    },
    {
      "number": 9,
      "id": "evil_spirit",
      "name": "Evil Spirit",
      "source_version": "075",
      "attack_damage": 45,
      "damage_type": "wizardry",
      "behavior": {
        "kind": "area_automatic",
        "area": {
          "geometry": {
            "kind": "none"
          },
          "deferred_hits": true,
          "delay_per_tile_ms": 100,
          "delay_between_hits_ms": 1000,
          "hits_per_target": [
            0,
            2
          ],
          "hits_per_attack_range": [
            0,
            0
          ],
          "hit_chance_per_distance": 0.7,
          "projectile_count": 1,
          "effect_range": 0
        }
      },
      "target": "explicit",
      "target_restriction": "none",
      "range": 6,
      "implicit_target_range": 0,
      "hits_per_attack": 1,
      "moves_to_target": false,
      "moves_target": false,
      "element": null,
      "skip_elemental_modifier": false,
      "effect": null,
      "requirements": [
        {
          "stat": "total_energy",
          "value": 220
        }
      ],
      "consume": [
        {
          "stat": "current_mana",
          "value": 90
        }
      ],
      "classes": [
        "dark_wizard",
        "magic_gladiator"
      ]
    },
    {
      "number": 10,
      "id": "hellfire",
      "name": "Hellfire",
      "source_version": "075",
      "attack_damage": 120,
      "damage_type": "wizardry",
      "behavior": {
        "kind": "area_automatic",
        "area": {
          "geometry": {
            "kind": "none"
          },
          "deferred_hits": false,
          "delay_per_tile_ms": 0,
          "delay_between_hits_ms": 0,
          "hits_per_target": [
            1,
            1
          ],
          "hits_per_attack_range": [
            0,
            0
          ],
          "hit_chance_per_distance": 1.0,
          "projectile_count": 1,
          "effect_range": 0
        }
      },
      "target": "explicit",
      "target_restriction": "none",
      "range": 0,
      "implicit_target_range": 0,
      "hits_per_attack": 1,
      "moves_to_target": false,
      "moves_target": false,
      "element": "fire",
      "skip_elemental_modifier": false,
      "effect": null,
      "requirements": [
        {
          "stat": "total_energy",
          "value": 260
        }
      ],
      "consume": [
        {
          "stat": "current_mana",
          "value": 160
        }
      ],
      "classes": [
        "dark_wizard",
        "magic_gladiator"
      ]
    },
    {
      "number": 11,
      "id": "power_wave",
      "name": "Power Wave",
      "source_version": "075",
      "attack_damage": 14,
      "damage_type": "wizardry",
      "behavior": {
        "kind": "direct_hit"
      },
      "target": "explicit",
      "target_restriction": "none",
      "range": 6,
      "implicit_target_range": 0,
      "hits_per_attack": 1,
      "moves_to_target": false,
      "moves_target": false,
      "element": null,
      "skip_elemental_modifier": false,
      "effect": null,
      "requirements": [
        {
          "stat": "total_energy",
          "value": 56
        }
      ],
      "consume": [
        {
          "stat": "current_mana",
          "value": 5
        }
      ],
      "classes": [
        "dark_wizard",
        "magic_gladiator"
      ]
    },
    {
      "number": 12,
      "id": "aqua_beam",
      "name": "Aqua Beam",
      "source_version": "075",
      "attack_damage": 80,
      "damage_type": "wizardry",
      "behavior": {
        "kind": "area_automatic",
        "area": {
          "geometry": {
            "kind": "frustum",
            "start_width": 1.5,
            "end_width": 1.5,
            "distance": 8.0
          },
          "deferred_hits": false,
          "delay_per_tile_ms": 0,
          "delay_between_hits_ms": 0,
          "hits_per_target": [
            1,
            1
          ],
          "hits_per_attack_range": [
            0,
            0
          ],
          "hit_chance_per_distance": 1.0,
          "projectile_count": 1,
          "effect_range": 0
        }
      },
      "target": "explicit",
      "target_restriction": "none",
      "range": 6,
      "implicit_target_range": 0,
      "hits_per_attack": 1,
      "moves_to_target": false,
      "moves_target": false,
      "element": "water",
      "skip_elemental_modifier": false,
      "effect": null,
      "requirements": [
        {
          "stat": "total_energy",
          "value": 345
        }
      ],
      "consume": [
        {
          "stat": "current_mana",
          "value": 140
        }
      ],
      "classes": [
        "dark_wizard",
        "magic_gladiator"
      ]
    },
    {
      "number": 13,
      "id": "cometfall",
      "name": "Cometfall",
      "source_version": "095d",
      "review": "095d source marks it a plain direct hit yet attaches target-area settings; encoded as area_automatic (AoE intent; the S6 dataset marks it an automatic-hits area skill)",
      "attack_damage": 70,
      "damage_type": "wizardry",
      "behavior": {
        "kind": "area_automatic",
        "area": {
          "geometry": {
            "kind": "circle",
            "diameter": 2.0
          },
          "deferred_hits": false,
          "delay_per_tile_ms": 0,
          "delay_between_hits_ms": 0,
          "hits_per_target": [
            1,
            1
          ],
          "hits_per_attack_range": [
            0,
            0
          ],
          "hit_chance_per_distance": 1.0,
          "projectile_count": 1,
          "effect_range": 0
        }
      },
      "target": "explicit",
      "target_restriction": "none",
      "range": 3,
      "implicit_target_range": 0,
      "hits_per_attack": 1,
      "moves_to_target": false,
      "moves_target": false,
      "element": "lightning",
      "skip_elemental_modifier": false,
      "effect": null,
      "requirements": [
        {
          "stat": "total_energy",
          "value": 436
        }
      ],
      "consume": [
        {
          "stat": "current_mana",
          "value": 150
        }
      ],
      "classes": [
        "dark_wizard",
        "magic_gladiator"
      ]
    },
    {
      "number": 14,
      "id": "inferno",
      "name": "Inferno",
      "source_version": "095d",
      "attack_damage": 100,
      "damage_type": "wizardry",
      "behavior": {
        "kind": "area_automatic",
        "area": {
          "geometry": {
            "kind": "none"
          },
          "deferred_hits": false,
          "delay_per_tile_ms": 0,
          "delay_between_hits_ms": 0,
          "hits_per_target": [
            1,
            1
          ],
          "hits_per_attack_range": [
            0,
            0
          ],
          "hit_chance_per_distance": 1.0,
          "projectile_count": 1,
          "effect_range": 0
        }
      },
      "target": "explicit",
      "target_restriction": "none",
      "range": 0,
      "implicit_target_range": 0,
      "hits_per_attack": 1,
      "moves_to_target": false,
      "moves_target": false,
      "element": "fire",
      "skip_elemental_modifier": false,
      "effect": null,
      "requirements": [
        {
          "stat": "total_energy",
          "value": 578
        }
      ],
      "consume": [
        {
          "stat": "current_mana",
          "value": 200
        }
      ],
      "classes": [
        "dark_wizard",
        "magic_gladiator"
      ]
    },
    {
      "number": 16,
      "id": "soul_barrier",
      "name": "Soul Barrier",
      "source_version": "s6",
      "review": "retail 0.97/1.0 Soul Master skill; absent from OpenMU 075/095d datasets, values from the S6 initializer",
      "attack_damage": 0,
      "damage_type": "none",
      "behavior": {
        "kind": "buff"
      },
      "target": "explicit",
      "target_restriction": "party",
      "range": 6,
      "implicit_target_range": 0,
      "hits_per_attack": 1,
      "moves_to_target": false,
      "moves_target": false,
      "element": null,
      "skip_elemental_modifier": false,
      "effect": "soul_barrier",
      "requirements": [
        {
          "stat": "total_energy",
          "value": 408
        }
      ],
      "consume": [
        {
          "stat": "current_mana",
          "value": 70
        },
        {
          "stat": "current_ability",
          "value": 22
        }
      ],
      "classes": [
        "soul_master"
      ]
    },
    {
      "number": 17,
      "id": "energy_ball",
      "name": "Energy Ball",
      "source_version": "075",
      "attack_damage": 3,
      "damage_type": "wizardry",
      "behavior": {
        "kind": "direct_hit"
      },
      "target": "explicit",
      "target_restriction": "none",
      "range": 6,
      "implicit_target_range": 0,
      "hits_per_attack": 1,
      "moves_to_target": false,
      "moves_target": false,
      "element": null,
      "skip_elemental_modifier": false,
      "effect": null,
      "requirements": [],
      "consume": [
        {
          "stat": "current_mana",
          "value": 1
        }
      ],
      "classes": [
        "dark_wizard",
        "magic_gladiator"
      ]
    },
    {
      "number": 18,
      "id": "defense",
      "name": "Defense",
      "source_version": "075",
      "attack_damage": 0,
      "damage_type": "none",
      "behavior": {
        "kind": "buff"
      },
      "target": "explicit",
      "target_restriction": "self",
      "range": 0,
      "implicit_target_range": 0,
      "hits_per_attack": 1,
      "moves_to_target": false,
      "moves_target": false,
      "element": null,
      "skip_elemental_modifier": false,
      "effect": "shield_defense",
      "requirements": [],
      "consume": [
        {
          "stat": "current_mana",
          "value": 30
        }
      ],
      "classes": [
        "dark_knight",
        "magic_gladiator"
      ]
    },
    {
      "number": 19,
      "id": "falling_slash",
      "name": "Falling Slash",
      "source_version": "075",
      "attack_damage": 0,
      "damage_type": "physical",
      "behavior": {
        "kind": "direct_hit"
      },
      "target": "explicit",
      "target_restriction": "none",
      "range": 3,
      "implicit_target_range": 0,
      "hits_per_attack": 1,
      "moves_to_target": true,
      "moves_target": true,
      "element": null,
      "skip_elemental_modifier": false,
      "effect": null,
      "requirements": [],
      "consume": [
        {
          "stat": "current_mana",
          "value": 9
        }
      ],
      "classes": [
        "dark_knight",
        "magic_gladiator"
      ]
    },
    {
      "number": 20,
      "id": "lunge",
      "name": "Lunge",
      "source_version": "075",
      "attack_damage": 0,
      "damage_type": "physical",
      "behavior": {
        "kind": "direct_hit"
      },
      "target": "explicit",
      "target_restriction": "none",
      "range": 2,
      "implicit_target_range": 0,
      "hits_per_attack": 1,
      "moves_to_target": true,
      "moves_target": true,
      "element": null,
      "skip_elemental_modifier": false,
      "effect": null,
      "requirements": [],
      "consume": [
        {
          "stat": "current_mana",
          "value": 9
        }
      ],
      "classes": [
        "dark_knight",
        "magic_gladiator"
      ]
    },
    {
      "number": 21,
      "id": "uppercut",
      "name": "Uppercut",
      "source_version": "075",
      "attack_damage": 0,
      "damage_type": "physical",
      "behavior": {
        "kind": "direct_hit"
      },
      "target": "explicit",
      "target_restriction": "none",
      "range": 2,
      "implicit_target_range": 0,
      "hits_per_attack": 1,
      "moves_to_target": true,
      "moves_target": true,
      "element": null,
      "skip_elemental_modifier": false,
      "effect": null,
      "requirements": [],
      "consume": [
        {
          "stat": "current_mana",
          "value": 8
        }
      ],
      "classes": [
        "dark_knight",
        "magic_gladiator"
      ]
    },
    {
      "number": 22,
      "id": "cyclone",
      "name": "Cyclone",
      "source_version": "075",
      "attack_damage": 0,
      "damage_type": "physical",
      "behavior": {
        "kind": "direct_hit"
      },
      "target": "explicit",
      "target_restriction": "none",
      "range": 2,
      "implicit_target_range": 0,
      "hits_per_attack": 1,
      "moves_to_target": true,
      "moves_target": true,
      "element": null,
      "skip_elemental_modifier": false,
      "effect": null,
      "requirements": [],
      "consume": [
        {
          "stat": "current_mana",
          "value": 9
        }
      ],
      "classes": [
        "dark_knight",
        "magic_gladiator"
      ]
    },
    {
      "number": 23,
      "id": "slash",
      "name": "Slash",
      "source_version": "075",
      "attack_damage": 0,
      "damage_type": "physical",
      "behavior": {
        "kind": "direct_hit"
      },
      "target": "explicit",
      "target_restriction": "none",
      "range": 2,
      "implicit_target_range": 0,
      "hits_per_attack": 1,
      "moves_to_target": true,
      "moves_target": true,
      "element": null,
      "skip_elemental_modifier": false,
      "effect": null,
      "requirements": [],
      "consume": [
        {
          "stat": "current_mana",
          "value": 10
        }
      ],
      "classes": [
        "dark_knight",
        "magic_gladiator"
      ]
    },
    {
      "number": 24,
      "id": "triple_shot",
      "name": "Triple Shot",
      "source_version": "075",
      "attack_damage": 0,
      "damage_type": "physical",
      "behavior": {
        "kind": "area_automatic",
        "area": {
          "geometry": {
            "kind": "frustum",
            "start_width": 1.0,
            "end_width": 4.5,
            "distance": 7.0
          },
          "deferred_hits": true,
          "delay_per_tile_ms": 50,
          "delay_between_hits_ms": 0,
          "hits_per_target": [
            1,
            3
          ],
          "hits_per_attack_range": [
            0,
            3
          ],
          "hit_chance_per_distance": 1.0,
          "projectile_count": 3,
          "effect_range": 0
        }
      },
      "target": "explicit",
      "target_restriction": "none",
      "range": 6,
      "implicit_target_range": 0,
      "hits_per_attack": 1,
      "moves_to_target": false,
      "moves_target": false,
      "element": null,
      "skip_elemental_modifier": false,
      "effect": null,
      "requirements": [],
      "consume": [
        {
          "stat": "current_mana",
          "value": 5
        }
      ],
      "classes": [
        "fairy_elf"
      ]
    },
    {
      "number": 26,
      "id": "heal",
      "name": "Heal",
      "source_version": "075",
      "attack_damage": 0,
      "damage_type": "none",
      "behavior": {
        "kind": "regeneration"
      },
      "target": "explicit",
      "target_restriction": "player",
      "range": 6,
      "implicit_target_range": 0,
      "hits_per_attack": 1,
      "moves_to_target": false,
      "moves_target": false,
      "element": null,
      "skip_elemental_modifier": false,
      "effect": "heal",
      "requirements": [
        {
          "stat": "total_energy",
          "value": 52
        }
      ],
      "consume": [
        {
          "stat": "current_mana",
          "value": 20
        }
      ],
      "classes": [
        "fairy_elf"
      ]
    },
    {
      "number": 27,
      "id": "greater_defense",
      "name": "Greater Defense",
      "source_version": "075",
      "attack_damage": 0,
      "damage_type": "none",
      "behavior": {
        "kind": "buff"
      },
      "target": "explicit",
      "target_restriction": "player",
      "range": 6,
      "implicit_target_range": 0,
      "hits_per_attack": 1,
      "moves_to_target": false,
      "moves_target": false,
      "element": null,
      "skip_elemental_modifier": false,
      "effect": "greater_defense",
      "requirements": [
        {
          "stat": "total_energy",
          "value": 72
        }
      ],
      "consume": [
        {
          "stat": "current_mana",
          "value": 30
        }
      ],
      "classes": [
        "fairy_elf"
      ]
    },
    {
      "number": 28,
      "id": "greater_damage",
      "name": "Greater Damage",
      "source_version": "075",
      "attack_damage": 0,
      "damage_type": "none",
      "behavior": {
        "kind": "buff"
      },
      "target": "explicit",
      "target_restriction": "player",
      "range": 6,
      "implicit_target_range": 0,
      "hits_per_attack": 1,
      "moves_to_target": false,
      "moves_target": false,
      "element": null,
      "skip_elemental_modifier": false,
      "effect": "greater_damage",
      "requirements": [
        {
          "stat": "total_energy",
          "value": 92
        }
      ],
      "consume": [
        {
          "stat": "current_mana",
          "value": 40
        }
      ],
      "classes": [
        "fairy_elf"
      ]
    },
    {
      "number": 30,
      "id": "summon_goblin",
      "name": "Summon Goblin",
      "source_version": "075",
      "attack_damage": 0,
      "damage_type": "none",
      "behavior": {
        "kind": "summon",
        "monster": 26
      },
      "target": "explicit",
      "target_restriction": "none",
      "range": 0,
      "implicit_target_range": 0,
      "hits_per_attack": 1,
      "moves_to_target": false,
      "moves_target": false,
      "element": null,
      "skip_elemental_modifier": false,
      "effect": null,
      "requirements": [
        {
          "stat": "total_energy",
          "value": 90
        }
      ],
      "consume": [
        {
          "stat": "current_mana",
          "value": 40
        }
      ],
      "classes": [
        "fairy_elf"
      ]
    },
    {
      "number": 31,
      "id": "summon_stone_golem",
      "name": "Summon Stone Golem",
      "source_version": "075",
      "attack_damage": 0,
      "damage_type": "none",
      "behavior": {
        "kind": "summon",
        "monster": 32
      },
      "target": "explicit",
      "target_restriction": "none",
      "range": 0,
      "implicit_target_range": 0,
      "hits_per_attack": 1,
      "moves_to_target": false,
      "moves_target": false,
      "element": null,
      "skip_elemental_modifier": false,
      "effect": null,
      "requirements": [
        {
          "stat": "total_energy",
          "value": 170
        }
      ],
      "consume": [
        {
          "stat": "current_mana",
          "value": 70
        }
      ],
      "classes": [
        "fairy_elf"
      ]
    },
    {
      "number": 32,
      "id": "summon_assassin",
      "name": "Summon Assassin",
      "source_version": "075",
      "attack_damage": 0,
      "damage_type": "none",
      "behavior": {
        "kind": "summon",
        "monster": 21
      },
      "target": "explicit",
      "target_restriction": "none",
      "range": 0,
      "implicit_target_range": 0,
      "hits_per_attack": 1,
      "moves_to_target": false,
      "moves_target": false,
      "element": null,
      "skip_elemental_modifier": false,
      "effect": null,
      "requirements": [
        {
          "stat": "total_energy",
          "value": 190
        }
      ],
      "consume": [
        {
          "stat": "current_mana",
          "value": 110
        }
      ],
      "classes": [
        "fairy_elf"
      ]
    },
    {
      "number": 33,
      "id": "summon_elite_yeti",
      "name": "Summon Elite Yeti",
      "source_version": "075",
      "attack_damage": 0,
      "damage_type": "none",
      "behavior": {
        "kind": "summon",
        "monster": 20
      },
      "target": "explicit",
      "target_restriction": "none",
      "range": 0,
      "implicit_target_range": 0,
      "hits_per_attack": 1,
      "moves_to_target": false,
      "moves_target": false,
      "element": null,
      "skip_elemental_modifier": false,
      "effect": null,
      "requirements": [
        {
          "stat": "total_energy",
          "value": 230
        }
      ],
      "consume": [
        {
          "stat": "current_mana",
          "value": 160
        }
      ],
      "classes": [
        "fairy_elf"
      ]
    },
    {
      "number": 34,
      "id": "summon_dark_knight",
      "name": "Summon Dark Knight",
      "source_version": "075",
      "attack_damage": 0,
      "damage_type": "none",
      "behavior": {
        "kind": "summon",
        "monster": 10
      },
      "target": "explicit",
      "target_restriction": "none",
      "range": 0,
      "implicit_target_range": 0,
      "hits_per_attack": 1,
      "moves_to_target": false,
      "moves_target": false,
      "element": null,
      "skip_elemental_modifier": false,
      "effect": null,
      "requirements": [
        {
          "stat": "total_energy",
          "value": 250
        }
      ],
      "consume": [
        {
          "stat": "current_mana",
          "value": 200
        }
      ],
      "classes": [
        "fairy_elf"
      ]
    },
    {
      "number": 35,
      "id": "summon_bali",
      "name": "Summon Bali",
      "source_version": "075",
      "attack_damage": 0,
      "damage_type": "none",
      "behavior": {
        "kind": "summon",
        "monster": 150
      },
      "target": "explicit",
      "target_restriction": "none",
      "range": 0,
      "implicit_target_range": 0,
      "hits_per_attack": 1,
      "moves_to_target": false,
      "moves_target": false,
      "element": null,
      "skip_elemental_modifier": false,
      "effect": null,
      "requirements": [
        {
          "stat": "total_energy",
          "value": 260
        }
      ],
      "consume": [
        {
          "stat": "current_mana",
          "value": 250
        }
      ],
      "classes": [
        "fairy_elf"
      ]
    },
    {
      "number": 39,
      "id": "ice_storm",
      "name": "Ice Storm",
      "source_version": "s6",
      "review": "retail 1.0-era Soul Master AoE; absent from 075/095d, values from S6",
      "attack_damage": 80,
      "damage_type": "wizardry",
      "behavior": {
        "kind": "area_automatic",
        "area": {
          "geometry": {
            "kind": "circle",
            "diameter": 3.0
          },
          "deferred_hits": true,
          "delay_per_tile_ms": 0,
          "delay_between_hits_ms": 0,
          "hits_per_target": [
            1,
            1
          ],
          "hits_per_attack_range": [
            0,
            0
          ],
          "hit_chance_per_distance": 1.0,
          "projectile_count": 1,
          "effect_range": 0
        }
      },
      "target": "explicit",
      "target_restriction": "none",
      "range": 6,
      "implicit_target_range": 0,
      "hits_per_attack": 1,
      "moves_to_target": false,
      "moves_target": false,
      "element": "ice",
      "skip_elemental_modifier": false,
      "effect": "iced",
      "requirements": [
        {
          "stat": "total_energy",
          "value": 849
        }
      ],
      "consume": [
        {
          "stat": "current_mana",
          "value": 100
        },
        {
          "stat": "current_ability",
          "value": 5
        }
      ],
      "classes": [
        "soul_master"
      ]
    },
    {
      "number": 40,
      "id": "nova",
      "name": "Nova",
      "source_version": "s6",
      "review": "retail 1.0 Soul Master skill; mana 15 = 180 per full 12-stage charge; stage damage feeds nova_stage_damage",
      "attack_damage": 0,
      "damage_type": "wizardry",
      "behavior": {
        "kind": "direct_hit"
      },
      "target": "explicit",
      "target_restriction": "none",
      "range": 6,
      "implicit_target_range": 0,
      "hits_per_attack": 1,
      "moves_to_target": false,
      "moves_target": false,
      "element": "fire",
      "skip_elemental_modifier": false,
      "effect": null,
      "damage_scaling": [
        {
          "stat": "total_strength",
          "operator": "multiply",
          "operand": 0.5
        },
        {
          "stat": "nova_stage_damage",
          "operator": "multiply",
          "operand": 1.0
        }
      ],
      "requirements": [
        {
          "stat": "level",
          "value": 100
        },
        {
          "stat": "total_energy",
          "value": 1052
        }
      ],
      "consume": [
        {
          "stat": "current_mana",
          "value": 15
        }
      ],
      "classes": [
        "soul_master"
      ]
    },
    {
      "number": 41,
      "id": "twisting_slash",
      "name": "Twisting Slash",
      "source_version": "095d",
      "attack_damage": 0,
      "damage_type": "physical",
      "behavior": {
        "kind": "area_automatic",
        "area": {
          "geometry": {
            "kind": "none"
          },
          "deferred_hits": false,
          "delay_per_tile_ms": 0,
          "delay_between_hits_ms": 0,
          "hits_per_target": [
            1,
            1
          ],
          "hits_per_attack_range": [
            0,
            0
          ],
          "hit_chance_per_distance": 1.0,
          "projectile_count": 1,
          "effect_range": 0
        }
      },
      "target": "explicit",
      "target_restriction": "none",
      "range": 2,
      "implicit_target_range": 0,
      "hits_per_attack": 1,
      "moves_to_target": false,
      "moves_target": false,
      "element": "wind",
      "skip_elemental_modifier": false,
      "effect": null,
      "requirements": [],
      "consume": [
        {
          "stat": "current_mana",
          "value": 10
        }
      ],
      "classes": [
        "dark_knight",
        "magic_gladiator"
      ]
    },
    {
      "number": 42,
      "id": "rageful_blow",
      "name": "Rageful Blow",
      "source_version": "s6",
      "review": "retail 0.97/1.0 Blade Knight skill; absent from 075/095d, values from S6",
      "attack_damage": 60,
      "damage_type": "physical",
      "behavior": {
        "kind": "area_automatic",
        "area": {
          "geometry": {
            "kind": "none"
          },
          "deferred_hits": false,
          "delay_per_tile_ms": 0,
          "delay_between_hits_ms": 0,
          "hits_per_target": [
            1,
            1
          ],
          "hits_per_attack_range": [
            0,
            0
          ],
          "hit_chance_per_distance": 1.0,
          "projectile_count": 1,
          "effect_range": 0
        }
      },
      "target": "explicit",
      "target_restriction": "none",
      "range": 3,
      "implicit_target_range": 0,
      "hits_per_attack": 1,
      "moves_to_target": false,
      "moves_target": false,
      "element": "earth",
      "skip_elemental_modifier": false,
      "effect": null,
      "requirements": [
        {
          "stat": "level",
          "value": 170
        }
      ],
      "consume": [
        {
          "stat": "current_mana",
          "value": 25
        },
        {
          "stat": "current_ability",
          "value": 20
        }
      ],
      "classes": [
        "blade_knight"
      ]
    },
    {
      "number": 43,
      "id": "death_stab",
      "name": "Death Stab",
      "source_version": "s6",
      "review": "retail 0.97/1.0 Blade Knight skill; absent from 075/095d, values from S6",
      "attack_damage": 70,
      "damage_type": "physical",
      "behavior": {
        "kind": "direct_hit"
      },
      "target": "explicit_with_implicit_in_range",
      "target_restriction": "none",
      "range": 2,
      "implicit_target_range": 1,
      "hits_per_attack": 1,
      "moves_to_target": false,
      "moves_target": false,
      "element": "wind",
      "skip_elemental_modifier": false,
      "effect": null,
      "requirements": [
        {
          "stat": "level",
          "value": 160
        }
      ],
      "consume": [
        {
          "stat": "current_mana",
          "value": 15
        },
        {
          "stat": "current_ability",
          "value": 12
        }
      ],
      "classes": [
        "blade_knight"
      ]
    },
    {
      "number": 47,
      "id": "impale",
      "name": "Impale",
      "source_version": "095d",
      "attack_damage": 15,
      "damage_type": "physical",
      "behavior": {
        "kind": "direct_hit"
      },
      "target": "explicit",
      "target_restriction": "none",
      "range": 3,
      "implicit_target_range": 0,
      "hits_per_attack": 1,
      "moves_to_target": false,
      "moves_target": false,
      "element": null,
      "skip_elemental_modifier": false,
      "effect": null,
      "requirements": [
        {
          "stat": "level",
          "value": 28
        }
      ],
      "consume": [
        {
          "stat": "current_mana",
          "value": 8
        }
      ],
      "classes": [
        "dark_knight",
        "magic_gladiator"
      ]
    },
    {
      "number": 48,
      "id": "swell_life",
      "name": "Swell Life",
      "source_version": "s6",
      "review": "retail 0.97/1.0 knight party buff (Greater Fortitude); absent from 075/095d, values from S6",
      "attack_damage": 0,
      "damage_type": "none",
      "behavior": {
        "kind": "buff"
      },
      "target": "implicit_party",
      "target_restriction": "none",
      "range": 0,
      "implicit_target_range": 0,
      "hits_per_attack": 1,
      "moves_to_target": false,
      "moves_target": false,
      "element": null,
      "skip_elemental_modifier": false,
      "effect": "swell_life",
      "requirements": [
        {
          "stat": "level",
          "value": 120
        }
      ],
      "consume": [
        {
          "stat": "current_mana",
          "value": 22
        },
        {
          "stat": "current_ability",
          "value": 24
        }
      ],
      "classes": [
        "dark_knight",
        "blade_knight"
      ]
    },
    {
      "number": 49,
      "id": "fire_breath",
      "name": "Fire Breath",
      "source_version": "095d",
      "attack_damage": 30,
      "damage_type": "physical",
      "behavior": {
        "kind": "direct_hit"
      },
      "target": "explicit",
      "target_restriction": "none",
      "range": 3,
      "implicit_target_range": 0,
      "hits_per_attack": 1,
      "moves_to_target": false,
      "moves_target": false,
      "element": null,
      "skip_elemental_modifier": false,
      "effect": null,
      "requirements": [
        {
          "stat": "level",
          "value": 110
        }
      ],
      "consume": [
        {
          "stat": "current_mana",
          "value": 9
        }
      ],
      "classes": [
        "dark_knight",
        "magic_gladiator"
      ]
    },
    {
      "number": 50,
      "id": "flame_of_evil_monster",
      "name": "Flame of Evil (Monster)",
      "source_version": "075",
      "attack_damage": 120,
      "damage_type": "none",
      "behavior": {
        "kind": "direct_hit"
      },
      "target": "explicit",
      "target_restriction": "none",
      "range": 0,
      "implicit_target_range": 0,
      "hits_per_attack": 1,
      "moves_to_target": false,
      "moves_target": false,
      "element": null,
      "skip_elemental_modifier": false,
      "effect": null,
      "requirements": [
        {
          "stat": "level",
          "value": 60
        },
        {
          "stat": "total_energy",
          "value": 100
        }
      ],
      "consume": [
        {
          "stat": "current_mana",
          "value": 160
        }
      ],
      "classes": []
    },
    {
      "number": 51,
      "id": "ice_arrow",
      "name": "Ice Arrow",
      "source_version": "s6",
      "review": "retail 1.0 Muse Elf skill; absent from 075/095d, values from S6; S6 skill_multiplier rebalance relationship not extracted (see gaps)",
      "attack_damage": 105,
      "damage_type": "physical",
      "behavior": {
        "kind": "direct_hit"
      },
      "target": "explicit",
      "target_restriction": "none",
      "range": 8,
      "implicit_target_range": 0,
      "hits_per_attack": 1,
      "moves_to_target": false,
      "moves_target": false,
      "element": "ice",
      "skip_elemental_modifier": false,
      "effect": "freeze",
      "requirements": [],
      "consume": [
        {
          "stat": "current_mana",
          "value": 10
        },
        {
          "stat": "current_ability",
          "value": 12
        }
      ],
      "classes": [
        "muse_elf"
      ]
    },
    {
      "number": 52,
      "id": "penetration",
      "name": "Penetration",
      "source_version": "s6",
      "review": "retail 1.0 elf skill; absent from 075/095d, values from S6; S6 skill_multiplier rebalance relationship not extracted (see gaps)",
      "attack_damage": 70,
      "damage_type": "physical",
      "behavior": {
        "kind": "area_automatic",
        "area": {
          "geometry": {
            "kind": "frustum",
            "start_width": 1.1,
            "end_width": 1.2,
            "distance": 8.0
          },
          "deferred_hits": true,
          "delay_per_tile_ms": 50,
          "delay_between_hits_ms": 0,
          "hits_per_target": [
            1,
            1
          ],
          "hits_per_attack_range": [
            0,
            0
          ],
          "hit_chance_per_distance": 1.0,
          "projectile_count": 1,
          "effect_range": 0
        }
      },
      "target": "explicit",
      "target_restriction": "none",
      "range": 6,
      "implicit_target_range": 0,
      "hits_per_attack": 1,
      "moves_to_target": false,
      "moves_target": false,
      "element": "wind",
      "skip_elemental_modifier": false,
      "effect": null,
      "requirements": [
        {
          "stat": "level",
          "value": 130
        }
      ],
      "consume": [
        {
          "stat": "current_mana",
          "value": 7
        },
        {
          "stat": "current_ability",
          "value": 9
        }
      ],
      "classes": [
        "fairy_elf",
        "muse_elf"
      ]
    },
    {
      "number": 55,
      "id": "fire_slash",
      "name": "Fire Slash",
      "source_version": "s6",
      "review": "retail 1.0-era Magic Gladiator skill; absent from 075/095d, values from S6",
      "attack_damage": 80,
      "damage_type": "physical",
      "behavior": {
        "kind": "area_automatic",
        "area": {
          "geometry": {
            "kind": "frustum",
            "start_width": 1.5,
            "end_width": 2.0,
            "distance": 2.0
          },
          "deferred_hits": false,
          "delay_per_tile_ms": 0,
          "delay_between_hits_ms": 0,
          "hits_per_target": [
            1,
            1
          ],
          "hits_per_attack_range": [
            0,
            0
          ],
          "hit_chance_per_distance": 1.0,
          "projectile_count": 1,
          "effect_range": 0
        }
      },
      "target": "explicit",
      "target_restriction": "none",
      "range": 2,
      "implicit_target_range": 0,
      "hits_per_attack": 1,
      "moves_to_target": false,
      "moves_target": false,
      "element": "fire",
      "skip_elemental_modifier": false,
      "effect": "defense_reduction",
      "requirements": [],
      "consume": [
        {
          "stat": "current_mana",
          "value": 15
        },
        {
          "stat": "current_ability",
          "value": 20
        }
      ],
      "classes": [
        "magic_gladiator"
      ]
    },
    {
      "number": 56,
      "id": "power_slash",
      "name": "Power Slash",
      "source_version": "s6",
      "review": "retail 1.0-era Magic Gladiator skill; absent from 075/095d, values from S6",
      "attack_damage": 0,
      "damage_type": "physical",
      "behavior": {
        "kind": "area_automatic",
        "area": {
          "geometry": {
            "kind": "frustum",
            "start_width": 1.0,
            "end_width": 6.0,
            "distance": 6.0
          },
          "deferred_hits": false,
          "delay_per_tile_ms": 0,
          "delay_between_hits_ms": 0,
          "hits_per_target": [
            1,
            1
          ],
          "hits_per_attack_range": [
            0,
            0
          ],
          "hit_chance_per_distance": 1.0,
          "projectile_count": 1,
          "effect_range": 0
        }
      },
      "target": "explicit",
      "target_restriction": "none",
      "range": 5,
      "implicit_target_range": 0,
      "hits_per_attack": 1,
      "moves_to_target": false,
      "moves_target": false,
      "element": null,
      "skip_elemental_modifier": false,
      "effect": null,
      "requirements": [],
      "consume": [
        {
          "stat": "current_mana",
          "value": 15
        }
      ],
      "classes": [
        "magic_gladiator"
      ]
    },
    {
      "number": 58,
      "id": "nova_start",
      "name": "Nova (Start)",
      "source_version": "s6",
      "review": "charge-phase companion of the Nova backport (skill 40); not on the curated list but Nova is unusable without it",
      "attack_damage": 0,
      "damage_type": "none",
      "behavior": {
        "kind": "other"
      },
      "target": "explicit",
      "target_restriction": "none",
      "range": 0,
      "implicit_target_range": 0,
      "hits_per_attack": 1,
      "moves_to_target": false,
      "moves_target": false,
      "element": null,
      "skip_elemental_modifier": false,
      "effect": null,
      "requirements": [
        {
          "stat": "level",
          "value": 100
        },
        {
          "stat": "total_energy",
          "value": 1052
        }
      ],
      "consume": [
        {
          "stat": "current_ability",
          "value": 45
        }
      ],
      "classes": [
        "soul_master"
      ]
    },
    {
      "number": 61,
      "id": "fire_burst",
      "name": "Fire Burst",
      "source_version": "s6",
      "review": "Dark Lord backport (DL is 0.97/1.0 content, only in the S6 dataset)",
      "attack_damage": 100,
      "damage_type": "physical",
      "behavior": {
        "kind": "direct_hit"
      },
      "target": "explicit_with_implicit_in_range",
      "target_restriction": "none",
      "range": 6,
      "implicit_target_range": 1,
      "hits_per_attack": 1,
      "moves_to_target": false,
      "moves_target": false,
      "element": null,
      "skip_elemental_modifier": false,
      "effect": null,
      "requirements": [
        {
          "stat": "total_energy",
          "value": 79
        }
      ],
      "consume": [
        {
          "stat": "current_mana",
          "value": 25
        }
      ],
      "classes": [
        "dark_lord"
      ]
    },
    {
      "number": 62,
      "id": "earthshake",
      "name": "Earthshake",
      "source_version": "s6",
      "review": "Dark Lord backport; S6 horse_level*10 damage term dropped (dark horse pet excluded pre-S3, see gaps)",
      "attack_damage": 150,
      "damage_type": "physical",
      "behavior": {
        "kind": "area_automatic",
        "area": {
          "geometry": {
            "kind": "circle",
            "diameter": 10.0
          },
          "deferred_hits": false,
          "delay_per_tile_ms": 0,
          "delay_between_hits_ms": 0,
          "hits_per_target": [
            1,
            1
          ],
          "hits_per_attack_range": [
            9,
            15
          ],
          "hit_chance_per_distance": 1.0,
          "projectile_count": 1,
          "effect_range": 0
        }
      },
      "target": "explicit",
      "target_restriction": "none",
      "range": 10,
      "implicit_target_range": 0,
      "hits_per_attack": 1,
      "moves_to_target": false,
      "moves_target": false,
      "element": "lightning",
      "skip_elemental_modifier": true,
      "effect": null,
      "damage_scaling": [
        {
          "stat": "total_strength",
          "operator": "multiply",
          "operand": 0.1
        },
        {
          "stat": "total_leadership",
          "operator": "multiply",
          "operand": 0.2
        }
      ],
      "requirements": [],
      "consume": [
        {
          "stat": "current_ability",
          "value": 50
        }
      ],
      "classes": [
        "dark_lord"
      ]
    },
    {
      "number": 63,
      "id": "summon",
      "name": "Summon",
      "source_version": "s6",
      "review": "Dark Lord backport; summons party members (not a monster summon), party-summon behavior is a rules concern",
      "attack_damage": 0,
      "damage_type": "none",
      "behavior": {
        "kind": "other"
      },
      "target": "explicit",
      "target_restriction": "none",
      "range": 0,
      "implicit_target_range": 0,
      "hits_per_attack": 1,
      "moves_to_target": false,
      "moves_target": false,
      "element": null,
      "skip_elemental_modifier": false,
      "effect": null,
      "requirements": [
        {
          "stat": "total_leadership",
          "value": 400
        },
        {
          "stat": "total_energy",
          "value": 153
        }
      ],
      "consume": [
        {
          "stat": "current_mana",
          "value": 70
        },
        {
          "stat": "current_ability",
          "value": 30
        }
      ],
      "classes": [
        "dark_lord"
      ]
    },
    {
      "number": 64,
      "id": "increase_critical_damage",
      "name": "Increase Critical Damage",
      "source_version": "s6",
      "review": "Dark Lord backport (DL is 0.97/1.0 content, only in the S6 dataset)",
      "attack_damage": 0,
      "damage_type": "none",
      "behavior": {
        "kind": "buff"
      },
      "target": "implicit_party",
      "target_restriction": "none",
      "range": 0,
      "implicit_target_range": 0,
      "hits_per_attack": 1,
      "moves_to_target": false,
      "moves_target": false,
      "element": null,
      "skip_elemental_modifier": false,
      "effect": "critical_damage_increase",
      "requirements": [
        {
          "stat": "total_leadership",
          "value": 300
        },
        {
          "stat": "total_energy",
          "value": 102
        }
      ],
      "consume": [
        {
          "stat": "current_mana",
          "value": 50
        },
        {
          "stat": "current_ability",
          "value": 50
        }
      ],
      "classes": [
        "dark_lord"
      ]
    },
    {
      "number": 77,
      "id": "infinity_arrow",
      "name": "Infinity Arrow",
      "source_version": "s6",
      "review": "retail 1.0 Muse Elf buff; absent from 075/095d, values from S6",
      "attack_damage": 0,
      "damage_type": "none",
      "behavior": {
        "kind": "buff"
      },
      "target": "explicit",
      "target_restriction": "self",
      "range": 6,
      "implicit_target_range": 0,
      "hits_per_attack": 1,
      "moves_to_target": false,
      "moves_target": false,
      "element": null,
      "skip_elemental_modifier": false,
      "effect": "infinite_arrow",
      "requirements": [
        {
          "stat": "level",
          "value": 220
        }
      ],
      "consume": [
        {
          "stat": "current_mana",
          "value": 50
        },
        {
          "stat": "current_ability",
          "value": 10
        }
      ],
      "classes": [
        "muse_elf"
      ]
    },
    {
      "number": 150,
      "id": "generic_monster_skill",
      "name": "Generic Monster Skill",
      "source_version": "s6",
      "review": "monster-only attack skill: 075/095d monster initializers (Death Gorgon/Balrog/Hydra and 095d bosses) set attack_skill 150, but only the S6 skills initializer defines it - upstream 075/095d lookup silently resolves to null (latent omission); backported so those attack_skill references resolve",
      "attack_damage": 0,
      "damage_type": "none",
      "behavior": {
        "kind": "other"
      },
      "target": "explicit",
      "target_restriction": "none",
      "range": 5,
      "implicit_target_range": 0,
      "hits_per_attack": 1,
      "moves_to_target": false,
      "moves_target": false,
      "element": null,
      "skip_elemental_modifier": false,
      "effect": null,
      "requirements": [],
      "consume": [],
      "classes": []
    }
  ]
}
